azure/mgmt/storagecache/__init__.py
azure/mgmt/storagecache/_configuration.py
azure/mgmt/storagecache/_patch.py
azure/mgmt/storagecache/_storage_cache_management_client.py
azure/mgmt/storagecache/_version.py
azure/mgmt/storagecache/py.typed
azure/mgmt/storagecache/_utils/__init__.py
azure/mgmt/storagecache/_utils/serialization.py
azure/mgmt/storagecache/_utils/utils.py
azure/mgmt/storagecache/aio/__init__.py
azure/mgmt/storagecache/aio/_configuration.py
azure/mgmt/storagecache/aio/_patch.py
azure/mgmt/storagecache/aio/_storage_cache_management_client.py
azure/mgmt/storagecache/aio/operations/__init__.py
azure/mgmt/storagecache/aio/operations/_aml_filesystems_operations.py
azure/mgmt/storagecache/aio/operations/_asc_operations_operations.py
azure/mgmt/storagecache/aio/operations/_asc_usages_operations.py
azure/mgmt/storagecache/aio/operations/_auto_export_jobs_operations.py
azure/mgmt/storagecache/aio/operations/_auto_import_jobs_operations.py
azure/mgmt/storagecache/aio/operations/_caches_operations.py
azure/mgmt/storagecache/aio/operations/_import_jobs_operations.py
azure/mgmt/storagecache/aio/operations/_operations.py
azure/mgmt/storagecache/aio/operations/_patch.py
azure/mgmt/storagecache/aio/operations/_skus_operations.py
azure/mgmt/storagecache/aio/operations/_storage_cache_management_client_operations.py
azure/mgmt/storagecache/aio/operations/_storage_target_operations.py
azure/mgmt/storagecache/aio/operations/_storage_targets_operations.py
azure/mgmt/storagecache/aio/operations/_usage_models_operations.py
azure/mgmt/storagecache/models/__init__.py
azure/mgmt/storagecache/models/_models_py3.py
azure/mgmt/storagecache/models/_patch.py
azure/mgmt/storagecache/models/_storage_cache_management_client_enums.py
azure/mgmt/storagecache/operations/__init__.py
azure/mgmt/storagecache/operations/_aml_filesystems_operations.py
azure/mgmt/storagecache/operations/_asc_operations_operations.py
azure/mgmt/storagecache/operations/_asc_usages_operations.py
azure_mgmt_storagecache-3.0.1.dist-info/licenses/LICENSE
azure_mgmt_storagecache-3.0.1.dist-info/METADATA
azure_mgmt_storagecache-3.0.1.dist-info/WHEEL
azure_mgmt_storagecache-3.0.1.dist-info/top_level.txt
azure_mgmt_storagecache-3.0.1.dist-info/RECORD
